MANIFEST.in
setup.py
little_questions/__init__.py
little_questions/settings.py
little_questions.egg-info/PKG-INFO
little_questions.egg-info/SOURCES.txt
little_questions.egg-info/dependency_links.txt
little_questions.egg-info/requires.txt
little_questions.egg-info/top_level.txt
little_questions/classifiers/__init__.py
little_questions/classifiers/features.py
little_questions/classifiers/pipelines.py
little_questions/classifiers/svm.py
little_questions/data/__init__.py
little_questions/data/__pycache__/__init__.cpython-38.pyc
little_questions/features/__init__.py
little_questions/features/preprocess.py
little_questions/features/word_vecs.py
little_questions/models/intent_cache/advice.hash
little_questions/models/intent_cache/advice.intent.ids
little_questions/models/intent_cache/advice.intent.net
little_questions/models/intent_cache/advice.pos
little_questions/models/intent_cache/advice.pos.{action}.l.ids
little_questions/models/intent_cache/advice.pos.{action}.l.net
little_questions/models/intent_cache/advice.pos.{action}.r.ids
little_questions/models/intent_cache/advice.pos.{action}.r.net
little_questions/models/intent_cache/age.hash
little_questions/models/intent_cache/age.intent.ids
little_questions/models/intent_cache/age.intent.net
little_questions/models/intent_cache/age.pos
little_questions/models/intent_cache/age.pos.{query}.l.ids
little_questions/models/intent_cache/age.pos.{query}.l.net
little_questions/models/intent_cache/age.pos.{query}.r.ids
little_questions/models/intent_cache/age.pos.{query}.r.net
little_questions/models/intent_cache/assign_entity.hash
little_questions/models/intent_cache/assign_entity.intent.ids
little_questions/models/intent_cache/assign_entity.intent.net
little_questions/models/intent_cache/assign_entity.pos
little_questions/models/intent_cache/assign_entity.pos.{statement}.l.ids
little_questions/models/intent_cache/assign_entity.pos.{statement}.l.net
little_questions/models/intent_cache/assign_entity.pos.{statement}.r.ids
little_questions/models/intent_cache/assign_entity.pos.{statement}.r.net
little_questions/models/intent_cache/causal_attribute.hash
little_questions/models/intent_cache/causal_attribute.intent.ids
