Metadata-Version: 1.0
Name: little-questions
Version: 0.6.0
Summary: question parser and classifier
Home-page: https://github.com/OpenJarbas/little_questions
Author: jarbasAI
Author-email: jarbasai@mailfence.com
License: Apache2.0
Platform: UNKNOWN
